HandTrackingSheerin/__init__.py
HandTrackingSheerin/hand_tracking_module.py
HandTrackingSheerin-0.1.0.dist-info/License.txt
HandTrackingSheerin-0.1.0.dist-info/METADATA
HandTrackingSheerin-0.1.0.dist-info/WHEEL
HandTrackingSheerin-0.1.0.dist-info/top_level.txt
HandTrackingSheerin-0.1.0.dist-info/RECORD
